scibot/__init__.py
scibot/anno.py
scibot/bookmarklet.py
scibot/bookmarklet_server.py
scibot/check.py
scibot/cli.py
scibot/config.py
scibot/dash.py
scibot/dashboard.py
scibot/db.py
scibot/export.py
scibot/extract.py
scibot/get_annos.py
scibot/release.py
scibot/rridxp.py
scibot/services.py
scibot/submit.py
scibot/sync.py
scibot/utils.py
scibot/workflow.py
scibot-0.0.1.data/scripts/scibot-bookmarklet
scibot-0.0.1.data/scripts/scibot-dashboard
scibot-0.0.1.dist-info/METADATA
scibot-0.0.1.dist-info/RECORD
scibot-0.0.1.dist-info/WHEEL
scibot-0.0.1.dist-info/entry_points.txt
scibot-0.0.1.dist-info/top_level.txt
