Metadata-Version: 2.1
Name: scibot
Version: 0.0.1
Summary: curation workflow automation and coordination
Home-page: https://github.com/SciCrunch/scibot
Author: Tom Gillespie
Author-email: tgbugs@gmail.com
License: Apache 2.0
Keywords: rrid curation biocuration hypothesis hypothes.is web annotation
Platform: UNKNOWN
Requires-Dist: curio
Requires-Dist: docopt
Requires-Dist: flask
Requires-Dist: gevent
Requires-Dist: gunicorn
Requires-Dist: hyputils
Requires-Dist: lxml
Requires-Dist: pyontutils
